beancounttriodos/__init__.py
beancounttriodos/importer.py
beancounttriodos-1.0.1.dist-info/LICENSE
beancounttriodos-1.0.1.dist-info/METADATA
beancounttriodos-1.0.1.dist-info/WHEEL
beancounttriodos-1.0.1.dist-info/top_level.txt
beancounttriodos-1.0.1.dist-info/RECORD
