Metadata-Version: 2.2
Name: beancounttriodos
Version: 1.0.1
Summary: CSV importer script from Triodos online banking for beancount
Author-email: R <contact+triodos-this-is-spam@vonshednob.cc>
License: MIT License
Project-URL: repository, https://codeberg.org/vonshednob/beancount-triodos-importer
Project-URL: issues, https://codeberg.org/vonshednob/beancount-triodos-importer/issues
Requires-Python: >=3.9
License-File: LICENSE
Requires-Dist: beangulp>=0.2.0
